{
	"cmake" : 
	{
		"generator" : 
		{
			"multiConfig" : false,
			"name" : "Ninja"
		},
		"paths" : 
		{
			"cmake" : "H:/Programmieren/JetBrains/CLion/bin/cmake/win/x64/bin/cmake.exe",
			"cpack" : "H:/Programmieren/JetBrains/CLion/bin/cmake/win/x64/bin/cpack.exe",
			"ctest" : "H:/Programmieren/JetBrains/CLion/bin/cmake/win/x64/bin/ctest.exe",
			"root" : "H:/Programmieren/JetBrains/CLion/bin/cmake/win/x64/share/cmake-3.26"
		},
		"version" : 
		{
			"isDirty" : false,
			"major" : 3,
			"minor" : 26,
			"patch" : 4,
			"string" : "3.26.4",
			"suffix" : ""
		}
	},
	"objects" : 
	[
		{
			"jsonFile" : "codemodel-v2-6a96e3b37d424febbf5d.json",
			"kind" : "codemodel",
			"version" : 
			{
				"major" : 2,
				"minor" : 5
			}
		},
		{
			"jsonFile" : "cache-v2-2b6bf3a514b36b3b6b05.json",
			"kind" : "cache",
			"version" : 
			{
				"major" : 2,
				"minor" : 0
			}
		},
		{
			"jsonFile" : "cmakeFiles-v1-17f4908dca1217b225eb.json",
			"kind" : "cmakeFiles",
			"version" : 
			{
				"major" : 1,
				"minor" : 0
			}
		},
		{
			"jsonFile" : "toolchains-v1-5bc7b7054c2d270eb39e.json",
			"kind" : "toolchains",
			"version" : 
			{
				"major" : 1,
				"minor" : 0
			}
		}
	],
	"reply" : 
	{
		"cache-v2" : 
		{
			"jsonFile" : "cache-v2-2b6bf3a514b36b3b6b05.json",
			"kind" : "cache",
			"version" : 
			{
				"major" : 2,
				"minor" : 0
			}
		},
		"cmakeFiles-v1" : 
		{
			"jsonFile" : "cmakeFiles-v1-17f4908dca1217b225eb.json",
			"kind" : "cmakeFiles",
			"version" : 
			{
				"major" : 1,
				"minor" : 0
			}
		},
		"codemodel-v2" : 
		{
			"jsonFile" : "codemodel-v2-6a96e3b37d424febbf5d.json",
			"kind" : "codemodel",
			"version" : 
			{
				"major" : 2,
				"minor" : 5
			}
		},
		"toolchains-v1" : 
		{
			"jsonFile" : "toolchains-v1-5bc7b7054c2d270eb39e.json",
			"kind" : "toolchains",
			"version" : 
			{
				"major" : 1,
				"minor" : 0
			}
		}
	}
}
